LICENCE.md
csql/_/__init__.py
csql/_/api.py
csql/_/input/__init__.py
csql/_/input/strparsing.py
csql/_/models/__init__.py
csql/_/models/dialect.py
csql/_/models/overrides.py
csql/_/models/query.py
csql/_/models/query_replacers.py
csql/_/persist/__init__.py
csql/_/persist/cacher.py
csql/_/renderer/__init__.py
csql/_/renderer/parameters.py
csql/_/renderer/query.py
csql/_/utils.py
csql/__init__.py
csql/contrib/__init__.py
csql/contrib/persist/__init__.py
csql/contrib/persist/snowflake.py
csql/contrib/render/__init__.py
csql/contrib/render/param/__init__.py
csql/dialect.py
csql/overrides.py
csql/persist.py
csql/render/__init__.py
csql/render/param.py
csql/render/query.py
csql-0.11.0.dist-info/WHEEL
csql-0.11.0.dist-info/METADATA
csql-0.11.0.dist-info/RECORD
