Metadata-Version: 2.1
Name: csql
Version: 0.11.0
Summary: Simple library for writing composeable SQL queries
Home-page: https://github.com/akdor1154/python-csql
License: LGPL-3.0-or-later
Keywords: sql,analytics
Author: Jarrad Whitaker
Author-email: akdor1154@gmail.com
Requires-Python: >=3.8,<4.0
Classifier: Development Status :: 3 - Alpha
Classifier: License :: OSI Approved :: GNU Lesser General Public License v3 or later (LGPLv3+)
Classifier: Operating System :: OS Independent
Classifier: Programming Language :: Python :: 3
Classifier: Programming Language :: Python :: 3.10
Classifier: Programming Language :: Python :: 3.8
Classifier: Programming Language :: Python :: 3.9
Classifier: Topic :: Database
Provides-Extra: docs
Provides-Extra: notebooks
Provides-Extra: pandas
Requires-Dist: Sphinx (>=4.3.1,<5.0.0); extra == "docs"
Requires-Dist: duckdb (>=0.3.1,<0.4.0); extra == "notebooks"
Requires-Dist: ipykernel (>=6.6.0,<7.0.0); extra == "notebooks"
Requires-Dist: myst-parser[linkify] (>=0.16.1,<0.17.0); extra == "docs"
Requires-Dist: openpyxl (>=3.0.9,<4.0.0); extra == "notebooks"
Requires-Dist: pandas (>=1.3.4,<2.0.0); extra == "pandas" or extra == "docs"
Requires-Dist: snowflake-connector-python (>=2.7.2,<3.0.0); extra == "docs"
Requires-Dist: sphinx-autobuild (>=2021.3.14,<2022.0.0); extra == "docs"
Requires-Dist: sphinx-external-toc (>=0.2.3,<0.3.0); extra == "docs"
Requires-Dist: sphinx-rtd-theme (>=1.0.0,<2.0.0); extra == "docs"
Project-URL: Repository, https://github.com/akdor1154/python-csql
